LICENSE.md
README.md
pyproject.toml
setup.cfg
setup.py
src/ewoksorangetemplate/__init__.py
src/ewoksorangetemplate.egg-info/PKG-INFO
src/ewoksorangetemplate.egg-info/SOURCES.txt
src/ewoksorangetemplate.egg-info/dependency_links.txt
src/ewoksorangetemplate.egg-info/entry_points.txt
src/ewoksorangetemplate.egg-info/namespace_packages.txt
src/ewoksorangetemplate.egg-info/requires.txt
src/ewoksorangetemplate.egg-info/top_level.txt
src/ewoksorangetemplate/tasks/__init__.py
src/ewoksorangetemplate/tasks/sumtask.py
src/ewoksorangetemplate/tests/__init__.py
src/ewoksorangetemplate/tests/conftest.py
src/ewoksorangetemplate/tests/test_sumtask.py
src/ewoksorangetemplate/tests/test_tutorials.py
src/orangecontrib/__init__.py
src/orangecontrib/ewoksorangetemplate/__init__.py
src/orangecontrib/ewoksorangetemplate/sumtask.py
src/orangecontrib/ewoksorangetemplate/categories/__init__.py
src/orangecontrib/ewoksorangetemplate/categories/examples1/__init__.py
src/orangecontrib/ewoksorangetemplate/categories/examples1/sumtask.py
src/orangecontrib/ewoksorangetemplate/categories/examples1/icons/__init__.py
src/orangecontrib/ewoksorangetemplate/categories/examples1/icons/category.svg
src/orangecontrib/ewoksorangetemplate/categories/examples1/icons/sum.png
src/orangecontrib/ewoksorangetemplate/categories/examples1/tutorials/__init__.py
src/orangecontrib/ewoksorangetemplate/categories/examples1/tutorials/examples1.ows
src/orangecontrib/ewoksorangetemplate/categories/examples2/__init__.py
src/orangecontrib/ewoksorangetemplate/categories/examples2/sumtask.py
src/orangecontrib/ewoksorangetemplate/categories/examples2/icons/__init__.py
src/orangecontrib/ewoksorangetemplate/categories/examples2/icons/category.svg
src/orangecontrib/ewoksorangetemplate/categories/examples2/icons/sum.png
src/orangecontrib/ewoksorangetemplate/categories/examples2/tutorials/__init__.py
src/orangecontrib/ewoksorangetemplate/categories/examples2/tutorials/examples2.ows
src/orangecontrib/ewoksorangetemplate/icons/__init__.py
src/orangecontrib/ewoksorangetemplate/icons/category.svg
src/orangecontrib/ewoksorangetemplate/icons/sum.png
src/orangecontrib/ewoksorangetemplate/tutorials/__init__.py
src/orangecontrib/ewoksorangetemplate/tutorials/examples.ows