Metadata-Version: 2.1
Name: ewoksorangetemplate
Version: 0.0.1a0
Summary: Template for projects that implement Ewoks tasks with Orange widgets
Home-page: https://gitlab.esrf.fr/workflow/ewoksorangetemplate/
Author: ESRF
Author-email: wout.de_nolf@esrf.fr
License: MIT
Project-URL: Source, https://gitlab.esrf.fr/workflow/ewoksorangetemplate/
Project-URL: Documentation, https://ewoksorangetemplate.readthedocs.io/
Project-URL: Tracker, https://gitlab.esrf.fr/workflow/ewoksorangetemplate/issues/
Keywords: orange3 add-on,ewoks
Classifier: Intended Audience :: Science/Research
Classifier: License :: OSI Approved :: MIT License
Classifier: Programming Language :: Python :: 3
Requires-Python: >=3.7
Provides-Extra: test
Provides-Extra: dev
Provides-Extra: doc
License-File: LICENSE.md
